{
    "merchant": {
        "id": 45,
        "name": "Walmart"
    },
    "transactions": [
        {
            "id": "66e35383-990c-4934-a766-c600ee632d27",
            "external_id": "2ca2fdd5-ec2c-47ef-813d-463ef3951b5f",
            "datetime": "2024-11-10T00:00:00+00:00",
            "url": "https://www.walmart.com/orders/123123123rand",
            "order_status": "ORDERED",
            "payment_methods": [
                {
                    "external_id": "323245",
                    "type": "CARD",
                    "brand": "EBT",
                    "last_four": "1111",
                    "name": null,
                    "transaction_amount": 32.23
                },
                {
                    "external_id": "592134",
                    "type": "CARD",
                    "brand": "AMEX",
                    "last_four": "1111",
                    "name": null,
                    "transaction_amount": 27.77
                }
            ],
            "price": {
                "sub_total": 60,
                "adjustments": [],
                "total": 60,
                "currency": "USD"
            },
            "products": [
                {
                    "external_id": "10315643",
                    "name": "Aleve Tablets with Easy Open Arthritis Cap, Naproxen Sodium, for Pain Relief, 200 Count",
                    "url": "https://www.walmart.com/ip/576115402",
                    "quantity": 1,
                    "eligibility": [],
                    "price": {
                        "sub_total": 30,
                        "total": 30,
                        "unit_price": 30
                    }
                },
                {
                    "external_id": "880919144",
                    "name": "Freshness Guaranteed Hawaiian Dinner Rolls, 16 oz, 12 Count (Regular)",
                    "url": "https://www.walmart.com/ip/880919144",
                    "quantity": 1,
                    "eligibility": [],
                    "price": {
                        "sub_total": 30,
                        "total": 30,
                        "unit_price": 30
                    }
                }
            ]
        },
        {
            "id": "de830907-c9ac-48d4-a88d-d5f99661067c",
            "external_id": "03a0fa46-5c53-4fdb-9f08-407308883244",
            "datetime": "2024-11-10T00:00:00+00:00",
            "url": "https://www.walmart.com/orders/123123123rand",
            "order_status": "SHIPPED",
            "payment_methods": [
                {
                    "external_id": "390281",
                    "type": "CARD",
                    "brand": "EBT",
                    "last_four": "1111",
                    "name": null,
                    "transaction_amount": 25
                },
                {
                    "external_id": "928044",
                    "type": "CARD",
                    "brand": "AMEX",
                    "last_four": "1111",
                    "name": null,
                    "transaction_amount": 25
                }
            ],
            "price": {
                "sub_total": 50,
                "adjustments": [],
                "total": 50,
                "currency": "USD"
            },
            "products": [
                {
                    "external_id": "10315643",
                    "name": "Aleve Tablets with Easy Open Arthritis Cap, Naproxen Sodium, for Pain Relief, 200 Count",
                    "url": "https://www.walmart.com/ip/576115402",
                    "quantity": 1,
                    "eligibility": [
                        "FSA/HSA"
                    ],
                    "price": {
                        "sub_total": 25,
                        "total": 25,
                        "unit_price": 25
                    }
                },
                {
                    "external_id": "880919144",
                    "name": "Freshness Guaranteed Hawaiian Dinner Rolls, 16 oz, 12 Count (Regular)",
                    "url": "https://www.walmart.com/ip/880919144",
                    "quantity": 1,
                    "eligibility": [],
                    "price": {
                        "sub_total": 25,
                        "total": 25,
                        "unit_price": 25
                    }
                }
            ]
        },
        {
            "id": "13512eb7-0d30-426c-a0d4-f511150df088",
            "external_id": "e0ef7b87-8e02-475d-8c35-866ba3c6e199",
            "datetime": "2024-11-10T00:00:00+00:00",
            "url": "https://www.walmart.com/orders/123123123rand",
            "order_status": "DELIVERED",
            "payment_methods": [
                {
                    "external_id": "182111",
                    "type": "CARD",
                    "brand": "EBT",
                    "last_four": "1111",
                    "name": null,
                    "transaction_amount": 20
                },
                {
                    "external_id": "837729",
                    "type": "CARD",
                    "brand": "AMEX",
                    "last_four": "1111",
                    "name": null,
                    "transaction_amount": 20
                }
            ],
            "price": {
                "sub_total": 40,
                "adjustments": [],
                "total": 40,
                "currency": "USD"
            },
            "products": [
                {
                    "external_id": "10315643",
                    "name": "Aleve Tablets with Easy Open Arthritis Cap, Naproxen Sodium, for Pain Relief, 200 Count",
                    "url": "https://www.walmart.com/ip/576115402",
                    "quantity": 1,
                    "eligibility": [
                        "FSA/HSA"
                    ],
                    "price": {
                        "sub_total": 20,
                        "total": 20,
                        "unit_price": 20
                    }
                },
                {
                    "external_id": "880919144",
                    "name": "Freshness Guaranteed Hawaiian Dinner Rolls, 16 oz, 12 Count (Regular)",
                    "url": "https://www.walmart.com/ip/880919144",
                    "quantity": 1,
                    "eligibility": [],
                    "price": {
                        "sub_total": 20,
                        "total": 20,
                        "unit_price": 20
                    }
                }
            ]
        },
        {
            "id": "e7d92b16-c3e6-46a6-955e-15e713b5cd4e",
            "external_id": "81598c0c-b3cb-4658-8deb-92cfbb305e2c",
            "datetime": "2024-11-10T00:00:00+00:00",
            "url": "https://www.walmart.com/orders/123123123rand",
            "order_status": "CANCELLED",
            "payment_methods": [
                {
                    "external_id": "392824",
                    "type": "CARD",
                    "brand": "AMEX",
                    "last_four": "1111",
                    "name": null,
                    "transaction_amount": null
                }
            ],
            "price": {
                "sub_total": 30,
                "adjustments": [],
                "total": 30,
                "currency": "USD"
            },
            "products": [
                {
                    "external_id": "10315643",
                    "name": "Aleve Tablets with Easy Open Arthritis Cap, Naproxen Sodium, for Pain Relief, 200 Count",
                    "url": "https://www.walmart.com/ip/576115402",
                    "quantity": 1,
                    "eligibility": [
                        "FSA/HSA"
                    ],
                    "price": {
                        "sub_total": 15,
                        "total": 15,
                        "unit_price": 15
                    }
                },
                {
                    "external_id": "880919144",
                    "name": "Freshness Guaranteed Hawaiian Dinner Rolls, 16 oz, 12 Count (Regular)",
                    "url": "https://www.walmart.com/ip/880919144",
                    "quantity": 1,
                    "eligibility": [],
                    "price": {
                        "sub_total": 15,
                        "total": 15,
                        "unit_price": 15
                    }
                }
            ]
        },
        {
            "id": "6be8b33c-effa-4304-a1b1-ea3913d15e92",
            "external_id": "a29b0f38-8ce3-46d7-aac4-546f34744ab2",
            "datetime": "2024-11-10T00:00:00+00:00",
            "url": "https://www.walmart.com/orders/123123123rand",
            "order_status": "COMPLETED",
            "payment_methods": [
                {
                    "external_id": "838812",
                    "type": "CARD",
                    "brand": "AMEX",
                    "last_four": "1111",
                    "name": null,
                    "transaction_amount": null
                }
            ],
            "price": {
                "sub_total": 20,
                "adjustments": [],
                "total": 20,
                "currency": "USD"
            },
            "products": [
                {
                    "external_id": "10315643",
                    "name": "Aleve Tablets with Easy Open Arthritis Cap, Naproxen Sodium, for Pain Relief, 200 Count",
                    "url": "https://www.walmart.com/ip/576115402",
                    "quantity": 1,
                    "eligibility": [
                        "FSA/HSA"
                    ],
                    "price": {
                        "sub_total": 10,
                        "total": 10,
                        "unit_price": 10
                    }
                },
                {
                    "external_id": "880919144",
                    "name": "Freshness Guaranteed Hawaiian Dinner Rolls, 16 oz, 12 Count (Regular)",
                    "url": "https://www.walmart.com/ip/880919144",
                    "quantity": 1,
                    "eligibility": [],
                    "price": {
                        "sub_total": 10,
                        "total": 10,
                        "unit_price": 10
                    }
                }
            ]
        }
    ],
    "next_cursor": "eyJpZCI6MTI3NjEsIl9wb2ludHNUb05leHRJdGVtcyI6dHJ1ZX0",
    "limit": 5
}